concrete_utils-0.0.10-py3.9-nspkg.pth
concrete/utils/__init__.py
concrete/utils/file.py
concrete_utils-0.0.10.dist-info/LICENSE
concrete_utils-0.0.10.dist-info/METADATA
concrete_utils-0.0.10.dist-info/WHEEL
concrete_utils-0.0.10.dist-info/namespace_packages.txt
concrete_utils-0.0.10.dist-info/top_level.txt
concrete_utils-0.0.10.dist-info/RECORD
